setup.py
bw/__init__.py
bw/__version__.py
bw/callback.py
bw/constant.py
bw/enum.py
bw/retrying.py
bw/utils.py
bw/api/__init__.py
bw/api/basic.py
bw/api/query.py
bw/api/trade.py
bw/csdk/__init__.py
bw/csdk/bwsdk.dll
bw/csdk/bwserver-term-linux.exe
bw/csdk/bwserver-term.exe
bw/csdk/concrt140.dll
bw/csdk/cpp_sdk.pyd
bw/csdk/cpp_sdk.so
bw/csdk/msvcp140.dll
bw/csdk/quoteManager-console.exe
bw/csdk/quoteManager.exe
bw/csdk/setup.py
bw/csdk/setup_linux.py
bw/csdk/vccorlib140.dll
bw/csdk/vcruntime140.dll
bw/model/__init__.py
bw/model/account.py
bw/model/fundamental.py
bw/model/history.py
bw/model/storage.py
bw/yy/__init__.py
bw/yy/account.py
bw/yy/common.py
bw/yy/data.py
bw/yy/fundamental.py
bw/yy/history.py
bw/yy/performance.py
bwtest.egg-info/PKG-INFO
bwtest.egg-info/SOURCES.txt
bwtest.egg-info/dependency_links.txt
bwtest.egg-info/requires.txt
bwtest.egg-info/top_level.txt